cplib/__init__.py
cplib-0.1.4.dist-info/METADATA
cplib-0.1.4.dist-info/WHEEL
cplib-0.1.4.dist-info/LICENSE
cplib-0.1.4.dist-info/RECORD
